<?xml version="1.0" encoding="windows-1252" ?>
<!DOCTYPE Entity SYSTEM "jbo_03_01.dtd">
<!---->
<Entity
  xmlns="http://xmlns.oracle.com/bc4j"
  Name="SrvDap"
  Version="12.1.2.66.68"
  InheritPersonalization="merge"
  DBObjectType="table"
  DBObjectName="SRV_DAP"
  AliasName="SrvDap"
  BindingStyle="OracleName"
  RowClass="dgcom.model.eo.srv.SrvDapImpl"
  xmlns:validation="http://xmlns.oracle.com/adfm/validation">
  <DesignTime>
    <Attr Name="_superClass" Value="dgcom.model.stand.DigicomEntityImpl"/>
    <Attr Name="_codeGenFlag2" Value="Init|Delete|Access|DML"/>
    <Attr Name="_isCodegen" Value="true"/>
  </DesignTime>
  <ViewAccessor
    Name="AccAllStoresDapStore"
    ViewObjectName="dgcom.model.vo.set.AllStoresVO"
    RowLevelBinds="true">
    <ViewCriteriaUsage
      Name="AllStoresStoreIdByLocation"
      FullName="dgcom.model.vo.set.AllStoresVO.AllStoresStoreIdByLocation"/>
    <ParameterMap>
      <PIMap Variable="P_ADF_LOCATIONID">
        <TransientExpression><![CDATA[Locationid]]></TransientExpression>
      </PIMap>
    </ParameterMap>
  </ViewAccessor>
  <Attribute
    Name="DapId"
    Precision="15"
    ColumnName="DAP_ID"
    SQLType="VARCHAR"
    Type="java.lang.String"
    ColumnType="VARCHAR2"
    TableName="SRV_DAP"
    PrimaryKey="true">
    <DesignTime>
      <Attr Name="_DisplaySize" Value="15"/>
    </DesignTime>
  </Attribute>
  <Attribute
    Name="Locationid"
    IsNotNull="true"
    Precision="15"
    ColumnName="LOCATIONID"
    SQLType="VARCHAR"
    Type="java.lang.String"
    ColumnType="VARCHAR2"
    TableName="SRV_DAP">
    <DesignTime>
      <Attr Name="_DisplaySize" Value="15"/>
    </DesignTime>
  </Attribute>
  <Attribute
    Name="Jobcardno"
    IsNotNull="true"
    Precision="15"
    ColumnName="JOBCARDNO"
    SQLType="VARCHAR"
    Type="java.lang.String"
    ColumnType="VARCHAR2"
    TableName="SRV_DAP">
    <DesignTime>
      <Attr Name="_DisplaySize" Value="15"/>
    </DesignTime>
  </Attribute>
  <Attribute
    Name="DapDate"
    IsNotNull="true"
    ColumnName="DAP_DATE"
    SQLType="DATE"
    Type="oracle.jbo.domain.Date"
    ColumnType="DATE"
    TableName="SRV_DAP">
    <TransientExpression><![CDATA[adf.currentDate]]></TransientExpression>
    <Properties>
      <SchemaBasedProperties>
        <LABEL
          ResId="dgcom.model.eo.srv.SrvDap.DapDate_LABEL"/>
        <DISPLAYWIDTH
          Value="30"/>
      </SchemaBasedProperties>
    </Properties>
    <validation:ValidationBean
      Name="DocumentDateEntryRights"
      ResId="dgcom.model.eo.srv.SrvJobcard.Jobdate_Rule_0"
      OnAttribute="DapDate"
      Version="2"
      OperandType="LITERAL"
      Inverse="false"
      DisplayName="RulCheckDateRights"
      ValidationBeanClass="dgcom.model.rules.RulCheckDateRights">
      <validation:OnCondition><![CDATA[newValue!=null]]></validation:OnCondition>
    </validation:ValidationBean>
  </Attribute>
  <Attribute
    Name="ChApproval"
    Precision="1"
    ColumnName="CH_APPROVAL"
    SQLType="VARCHAR"
    Type="java.lang.String"
    ColumnType="VARCHAR2"
    TableName="SRV_DAP"
    DefaultValue="N">
    <DesignTime>
      <Attr Name="_DisplaySize" Value="1"/>
    </DesignTime>
  </Attribute>
  <Attribute
    Name="ChRemarks"
    Precision="200"
    ColumnName="CH_REMARKS"
    SQLType="VARCHAR"
    Type="java.lang.String"
    ColumnType="VARCHAR2"
    TableName="SRV_DAP">
    <DesignTime>
      <Attr Name="_DisplaySize" Value="200"/>
    </DesignTime>
  </Attribute>
  <Attribute
    Name="BhApproval"
    Precision="1"
    ColumnName="BH_APPROVAL"
    SQLType="VARCHAR"
    Type="java.lang.String"
    ColumnType="VARCHAR2"
    TableName="SRV_DAP"
    DefaultValue="N">
    <DesignTime>
      <Attr Name="_DisplaySize" Value="1"/>
    </DesignTime>
  </Attribute>
  <Attribute
    Name="BhRemarks"
    Precision="200"
    ColumnName="BH_REMARKS"
    SQLType="VARCHAR"
    Type="java.lang.String"
    ColumnType="VARCHAR2"
    TableName="SRV_DAP">
    <DesignTime>
      <Attr Name="_DisplaySize" Value="200"/>
    </DesignTime>
    <Properties>
      <SchemaBasedProperties>
        <DISPLAYWIDTH
          Value="30"/>
        <LABEL
          ResId="dgcom.model.eo.srv.SrvDap.BhRemarks_LABEL"/>
      </SchemaBasedProperties>
    </Properties>
  </Attribute>
  <Attribute
    Name="RhApproval"
    Precision="1"
    ColumnName="RH_APPROVAL"
    SQLType="VARCHAR"
    Type="java.lang.String"
    ColumnType="VARCHAR2"
    TableName="SRV_DAP"
    DefaultValue="N">
    <DesignTime>
      <Attr Name="_DisplaySize" Value="1"/>
    </DesignTime>
  </Attribute>
  <Attribute
    Name="RhRemarks"
    Precision="200"
    ColumnName="RH_REMARKS"
    SQLType="VARCHAR"
    Type="java.lang.String"
    ColumnType="VARCHAR2"
    TableName="SRV_DAP">
    <DesignTime>
      <Attr Name="_DisplaySize" Value="200"/>
    </DesignTime>
    <Properties>
      <SchemaBasedProperties>
        <DISPLAYWIDTH
          Value="30"/>
      </SchemaBasedProperties>
    </Properties>
  </Attribute>
  <Attribute
    Name="PrevDoctype"
    Precision="15"
    ColumnName="PREV_DOCTYPE"
    SQLType="VARCHAR"
    Type="java.lang.String"
    ColumnType="VARCHAR2"
    TableName="SRV_DAP">
    <DesignTime>
      <Attr Name="_DisplaySize" Value="15"/>
    </DesignTime>
  </Attribute>
  <Attribute
    Name="PrevDocid"
    Precision="15"
    ColumnName="PREV_DOCID"
    SQLType="VARCHAR"
    Type="java.lang.String"
    ColumnType="VARCHAR2"
    TableName="SRV_DAP">
    <DesignTime>
      <Attr Name="_DisplaySize" Value="15"/>
    </DesignTime>
  </Attribute>
  <Attribute
    Name="Posted"
    IsNotNull="true"
    Precision="1"
    ColumnName="POSTED"
    SQLType="VARCHAR"
    Type="java.lang.String"
    ColumnType="VARCHAR2"
    TableName="SRV_DAP"
    DefaultValue="N">
    <DesignTime>
      <Attr Name="_DisplaySize" Value="1"/>
    </DesignTime>
    <Properties>
      <SchemaBasedProperties>
        <LABEL
          ResId="dgcom.model.eo.srv.SrvDap.Posted_LABEL"/>
      </SchemaBasedProperties>
    </Properties>
  </Attribute>
  <Attribute
    Name="Postedby"
    Precision="20"
    ColumnName="POSTEDBY"
    SQLType="VARCHAR"
    Type="java.lang.String"
    ColumnType="VARCHAR2"
    TableName="SRV_DAP">
    <DesignTime>
      <Attr Name="_DisplaySize" Value="20"/>
    </DesignTime>
  </Attribute>
  <Attribute
    Name="Createdby"
    Precision="20"
    ColumnName="CREATEDBY"
    SQLType="VARCHAR"
    Type="java.lang.String"
    ColumnType="VARCHAR2"
    TableName="SRV_DAP">
    <DesignTime>
      <Attr Name="_DisplaySize" Value="20"/>
    </DesignTime>
  </Attribute>
  <Attribute
    Name="CreatedDate"
    ColumnName="CREATED_DATE"
    SQLType="DATE"
    Type="oracle.jbo.domain.Date"
    ColumnType="DATE"
    TableName="SRV_DAP"/>
  <Attribute
    Name="Modifiedby"
    Precision="20"
    ColumnName="MODIFIEDBY"
    SQLType="VARCHAR"
    Type="java.lang.String"
    ColumnType="VARCHAR2"
    TableName="SRV_DAP">
    <DesignTime>
      <Attr Name="_DisplaySize" Value="20"/>
    </DesignTime>
  </Attribute>
  <Attribute
    Name="ModifiedDate"
    ColumnName="MODIFIED_DATE"
    SQLType="DATE"
    Type="oracle.jbo.domain.Date"
    ColumnType="DATE"
    TableName="SRV_DAP"/>
  <Attribute
    Name="Customerid"
    Precision="15"
    ColumnName="CUSTOMERID"
    SQLType="VARCHAR"
    Type="java.lang.String"
    ColumnType="VARCHAR2"
    TableName="SRV_DAP">
    <DesignTime>
      <Attr Name="_DisplaySize" Value="15"/>
    </DesignTime>
  </Attribute>
  <Attribute
    Name="Salespersonid"
    Precision="15"
    ColumnName="SALESPERSONID"
    SQLType="VARCHAR"
    Type="java.lang.String"
    ColumnType="VARCHAR2"
    TableName="SRV_DAP">
    <DesignTime>
      <Attr Name="_DisplaySize" Value="15"/>
    </DesignTime>
  </Attribute>
  <Attribute
    Name="Salesterritoryid"
    Precision="15"
    ColumnName="SALESTERRITORYID"
    SQLType="VARCHAR"
    Type="java.lang.String"
    ColumnType="VARCHAR2"
    TableName="SRV_DAP">
    <DesignTime>
      <Attr Name="_DisplaySize" Value="15"/>
    </DesignTime>
  </Attribute>
  <Attribute
    Name="Pid"
    Precision="5"
    Scale="0"
    ColumnName="PID"
    SQLType="NUMERIC"
    Type="java.lang.Integer"
    ColumnType="NUMBER"
    TableName="SRV_DAP"/>
  <Attribute
    Name="Storeid"
    Precision="15"
    ColumnName="STOREID"
    SQLType="VARCHAR"
    Type="java.lang.String"
    ColumnType="VARCHAR2"
    TableName="SRV_DAP">
    <DesignTime>
      <Attr Name="_DisplaySize" Value="15"/>
    </DesignTime>
  </Attribute>
  <Attribute
    Name="IsMigrated"
    Precision="1"
    ColumnName="IS_MIGRATED"
    SQLType="VARCHAR"
    Type="java.lang.String"
    ColumnType="VARCHAR2"
    TableName="SRV_DAP">
    <DesignTime>
      <Attr Name="_DisplaySize" Value="1"/>
    </DesignTime>
  </Attribute>
  <Attribute
    Name="MigratedDate"
    ColumnName="MIGRATED_DATE"
    SQLType="DATE"
    Type="oracle.jbo.domain.Date"
    ColumnType="DATE"
    TableName="SRV_DAP"/>
  <Attribute
    Name="Box"
    Precision="1"
    ColumnName="BOX"
    SQLType="VARCHAR"
    Type="java.lang.String"
    ColumnType="VARCHAR2"
    TableName="SRV_DAP"
    DefaultValue="N">
    <DesignTime>
      <Attr Name="_DisplaySize" Value="1"/>
    </DesignTime>
  </Attribute>
  <Attribute
    Name="Handfree"
    Precision="1"
    ColumnName="HANDFREE"
    SQLType="VARCHAR"
    Type="java.lang.String"
    ColumnType="VARCHAR2"
    TableName="SRV_DAP"
    DefaultValue="N">
    <DesignTime>
      <Attr Name="_DisplaySize" Value="1"/>
    </DesignTime>
    <Properties>
      <SchemaBasedProperties>
        <LABEL
          ResId="dgcom.model.eo.srv.SrvDap.Handfree_LABEL"/>
      </SchemaBasedProperties>
    </Properties>
  </Attribute>
  <Attribute
    Name="Battery"
    Precision="1"
    ColumnName="BATTERY"
    SQLType="VARCHAR"
    Type="java.lang.String"
    ColumnType="VARCHAR2"
    TableName="SRV_DAP"
    DefaultValue="N">
    <DesignTime>
      <Attr Name="_DisplaySize" Value="1"/>
    </DesignTime>
  </Attribute>
  <Attribute
    Name="BackCover"
    Precision="1"
    ColumnName="BACK_COVER"
    SQLType="VARCHAR"
    Type="java.lang.String"
    ColumnType="VARCHAR2"
    TableName="SRV_DAP"
    DefaultValue="N">
    <DesignTime>
      <Attr Name="_DisplaySize" Value="1"/>
    </DesignTime>
  </Attribute>
  <Attribute
    Name="WarrantyCard"
    Precision="1"
    ColumnName="WARRANTY_CARD"
    SQLType="VARCHAR"
    Type="java.lang.String"
    ColumnType="VARCHAR2"
    TableName="SRV_DAP"
    DefaultValue="N">
    <DesignTime>
      <Attr Name="_DisplaySize" Value="1"/>
    </DesignTime>
  </Attribute>
  <Attribute
    Name="Pop"
    Precision="1"
    ColumnName="POP"
    SQLType="VARCHAR"
    Type="java.lang.String"
    ColumnType="VARCHAR2"
    TableName="SRV_DAP"
    DefaultValue="N">
    <DesignTime>
      <Attr Name="_DisplaySize" Value="1"/>
    </DesignTime>
    <Properties>
      <SchemaBasedProperties>
        <LABEL
          ResId="dgcom.model.eo.srv.SrvDap.Pop_LABEL"/>
      </SchemaBasedProperties>
    </Properties>
  </Attribute>
  <Attribute
    Name="Charger"
    Precision="1"
    ColumnName="CHARGER"
    SQLType="VARCHAR"
    Type="java.lang.String"
    ColumnType="VARCHAR2"
    TableName="SRV_DAP"
    DefaultValue="N">
    <DesignTime>
      <Attr Name="_DisplaySize" Value="1"/>
    </DesignTime>
    <Properties>
      <SchemaBasedProperties>
        <DISPLAYWIDTH
          Value="30"/>
      </SchemaBasedProperties>
    </Properties>
  </Attribute>
  <Attribute
    Name="DataCable"
    Precision="1"
    ColumnName="DATA_CABLE"
    SQLType="VARCHAR"
    Type="java.lang.String"
    ColumnType="VARCHAR2"
    TableName="SRV_DAP"
    DefaultValue="N">
    <DesignTime>
      <Attr Name="_DisplaySize" Value="1"/>
    </DesignTime>
    <Properties>
      <SchemaBasedProperties>
        <LABEL
          ResId="dgcom.model.eo.srv.SrvDap.DataCable_LABEL"/>
      </SchemaBasedProperties>
    </Properties>
  </Attribute>
  <Attribute
    Name="Technicianid"
    IsNotNull="true"
    Precision="15"
    ColumnName="TECHNICIANID"
    SQLType="VARCHAR"
    Type="java.lang.String"
    ColumnType="VARCHAR2"
    TableName="SRV_DAP">
    <DesignTime>
      <Attr Name="_DisplaySize" Value="15"/>
    </DesignTime>
    <Properties>
      <SchemaBasedProperties>
        <LABEL
          ResId="dgcom.model.eo.srv.SrvDap.Technicianid_LABEL"/>
        <DISPLAYWIDTH
          Value="30"/>
      </SchemaBasedProperties>
    </Properties>
  </Attribute>
  <Attribute
    Name="Salesorderid"
    Precision="18"
    ColumnName="SALESORDERID"
    SQLType="VARCHAR"
    Type="java.lang.String"
    ColumnType="VARCHAR2"
    TableName="SRV_DAP">
    <DesignTime>
      <Attr Name="_DisplaySize" Value="18"/>
    </DesignTime>
  </Attribute>
  <AccessorAttribute
    Name="SrvJobcard"
    Association="dgcom.model.asso.srv.SysC0069068Assoc"
    AssociationEnd="dgcom.model.asso.srv.SysC0069068Assoc.SrvJobcard"
    AssociationOtherEnd="dgcom.model.asso.srv.SysC0069068Assoc.SrvDap"
    Type="dgcom.model.eo.srv.SrvJobcardImpl"
    IsUpdateable="true"/>
  <Key
    Name="SysC0069067"
    PrimaryKey="true">
    <DesignTime>
      <Attr Name="_DBObjectName" Value="SYS_C0069067"/>
    </DesignTime>
    <AttrArray Name="Attributes">
      <Item Value="dgcom.model.eo.srv.SrvDap.DapId"/>
    </AttrArray>
  </Key>
  <Key
    Name="SysC0069068">
    <DesignTime>
      <Attr Name="_referencedKey" Value="SYS_C0014094"/>
      <Attr Name="_isForeign" Value="true"/>
      <Attr Name="_DBObjectName" Value="SYS_C0069068"/>
    </DesignTime>
    <AttrArray Name="Attributes">
      <Item Value="dgcom.model.eo.srv.SrvDap.Jobcardno"/>
    </AttrArray>
  </Key>
  <Key
    Name="SysC0069069">
    <DesignTime>
      <Attr Name="_referencedKey" Value="XPKALL_LOCATIONS"/>
      <Attr Name="_isForeign" Value="true"/>
      <Attr Name="_DBObjectName" Value="SYS_C0069069"/>
    </DesignTime>
    <AttrArray Name="Attributes">
      <Item Value="dgcom.model.eo.srv.SrvDap.Locationid"/>
    </AttrArray>
  </Key>
  <Key
    Name="SysC0074594">
    <DesignTime>
      <Attr Name="_referencedKey" Value="SYS_C0014313"/>
      <Attr Name="_isForeign" Value="true"/>
      <Attr Name="_DBObjectName" Value="SYS_C0074594"/>
    </DesignTime>
    <AttrArray Name="Attributes">
      <Item Value="dgcom.model.eo.srv.SrvDap.Technicianid"/>
    </AttrArray>
  </Key>
  <validation:ValidationBean
    Name="SupervisionBackDAte"
    ResId="dgcom.model.eo.srv.SrvDap_Rule_0"
    OnAttribute="SrvDap"
    Version="2"
    OperandType="LITERAL"
    Inverse="false"
    DisplayName="RulCheckDateRights"
    ValidationBeanClass="dgcom.model.rules.RulCheckDateRights">
    <validation:OnAttributes>
      <validation:Item
        Value="Posted"/>
    </validation:OnAttributes>
    <validation:OnCondition><![CDATA[Posted=='Y']]></validation:OnCondition>
  </validation:ValidationBean>
  <ResourceBundle>
    <PropertiesBundle
      PropertiesFile="dgcom.model.ModelBundle"/>
  </ResourceBundle>
</Entity>
