<?xml version="1.0" encoding="windows-1252" ?>
<!DOCTYPE ViewObject SYSTEM "jbo_03_01.dtd">
<!---->
<ViewObject
  xmlns="http://xmlns.oracle.com/bc4j"
  Name="InPartsVO"
  Version="12.1.2.66.68"
  InheritPersonalization="merge"
  SelectList="InParts.PARTID, 
       InParts.PROD_ID, 
       InParts.PARTCATID, 
       InParts.UOMSID, 
       InParts.DESCRIPTION, 
       InParts.SPECIFICATION, 
       InParts.PART_REF_ID, 
       InParts.PARTNO, 
       InParts.CHILDPARTNO, 
       InParts.PARTWEIGHT, 
       InParts.LASTPURCHRATE, 
       InParts.LEAD_TIME, 
       InParts.DUTY_PR, 
       InParts.IB_PR, 
       InParts.STAX, 
       InParts.ITAX, 
       InParts.HSCODE, 
       InParts.HS_RATE, 
       InParts.PGLCODE, 
       InParts.PCCENTER, 
       InParts.CREATEDBY, 
       InParts.CREATED_DATE, 
       InParts.MODIFIEDBY, 
       InParts.MODIFIED_DATE, 
       InParts.NEEDAPPROVAL, 
       InParts.ITEMID"
  FromList="IN_PARTS InParts"
  BindingStyle="OracleName"
  CustomQuery="false"
  PageIterMode="Full"
  ComponentClass="dgcom.model.vo.srv.InPartsVOImpl"
  ComponentInterface="dgcom.model.vo.srv.common.InPartsVO"
  ClientProxyName="dgcom.model.vo.srv.client.InPartsVOClient">
  <DesignTime>
    <Attr Name="_codeGenFlag2" Value="Coll|VarAccess"/>
  </DesignTime>
  <Variable
    Name="P_ADF_ITEMID"
    Kind="viewcriteria"
    Type="java.lang.String"/>
  <Variable
    Name="P_ADF_CATID"
    Kind="viewcriteria"
    Type="java.lang.String"/>
  <ViewAccessor
    Name="AccSrvAllProdcategory"
    ViewObjectName="dgcom.model.vo.inv.AllProdcategoryVO"
    RowLevelBinds="true"/>
  <ViewAccessor
    Name="AccSrvPartcategory"
    ViewObjectName="dgcom.model.vo.srv.SrvPartcategoryVO"
    RowLevelBinds="true"/>
  <ViewAccessor
    Name="AccSrvInItemsInparts"
    ViewObjectName="dgcom.model.vo.inv.InItemsVO"
    RowLevelBinds="true">
    <ViewCriteriaUsage
      Name="InItemsExistsInServiceAndSrvBOM"
      FullName="dgcom.model.vo.inv.InItemsVO.InItemsExistsInServiceAndSrvBOM"/>
    <ParameterMap>
      <PIMap Variable="P_ADF_PROD_ID">
        <TransientExpression><![CDATA[ProdId]]></TransientExpression>
      </PIMap>
    </ParameterMap>
  </ViewAccessor>
  <ListBinding
    Name="LovSysProdCatagory"
    ListVOName="AccSrvAllProdcategory"
    ListRangeSize="-1"
    NullValueFlag="none"
    MRUCount="0"
    ComboRowCountHint="10">
    <AttrArray Name="AttrNames">
      <Item Value="ProdId"/>
    </AttrArray>
    <AttrArray Name="AttrExpressions"/>
    <AttrArray Name="ListAttrNames">
      <Item Value="ProdId"/>
    </AttrArray>
    <AttrArray Name="ListDisplayAttrNames">
      <Item Value="ProdId"/>
      <Item Value="Description"/>
    </AttrArray>
    <DisplayCriteria/>
  </ListBinding>
  <ListBinding
    Name="LovSysPartCatagory"
    ListVOName="AccSrvPartcategory"
    ListRangeSize="-1"
    NullValueFlag="none"
    MRUCount="0"
    ComboRowCountHint="10">
    <AttrArray Name="AttrNames">
      <Item Value="Partcatid"/>
    </AttrArray>
    <AttrArray Name="AttrExpressions"/>
    <AttrArray Name="ListAttrNames">
      <Item Value="Partcatid"/>
    </AttrArray>
    <AttrArray Name="ListDisplayAttrNames">
      <Item Value="Description"/>
    </AttrArray>
    <DisplayCriteria/>
  </ListBinding>
  <ListBinding
    Name="LovModelInparts"
    ListVOName="AccSrvInItemsInparts"
    ListRangeSize="-1"
    ComboRowCountHint="10"
    NullValueFlag="none"
    MRUCount="0">
    <AttrArray Name="AttrNames">
      <Item Value="txtModel"/>
    </AttrArray>
    <AttrArray Name="AttrExpressions"/>
    <AttrArray Name="DerivedAttrNames">
      <Item Value="Itemid"/>
    </AttrArray>
    <AttrArray Name="ListAttrNames">
      <Item Value="ModelNo"/>
      <Item Value="Itemid"/>
    </AttrArray>
    <AttrArray Name="ListDisplayAttrNames">
      <Item Value="ModelNo"/>
      <Item Value="ItemRefId"/>
      <Item Value="Itemid"/>
    </AttrArray>
    <DisplayCriteria
      Hint="showAndExecute"
      Name="InItemsVOFindVC"/>
  </ListBinding>
  <EntityUsage
    Name="InParts"
    Entity="dgcom.model.eo.srv.InParts"/>
  <ViewAttribute
    Name="Partid"
    IsNotNull="true"
    PrecisionRule="true"
    EntityAttrName="Partid"
    EntityUsage="InParts"
    AliasName="PARTID"/>
  <ViewAttribute
    Name="ProdId"
    IsNotNull="true"
    PrecisionRule="true"
    EntityAttrName="ProdId"
    EntityUsage="InParts"
    AliasName="PROD_ID"
    LOVName="LovSysProdCatagory">
    <Properties>
      <SchemaBasedProperties>
        <CONTROLTYPE
          Value="input_text_lov"/>
      </SchemaBasedProperties>
    </Properties>
  </ViewAttribute>
  <ViewAttribute
    Name="Partcatid"
    IsNotNull="true"
    PrecisionRule="true"
    EntityAttrName="Partcatid"
    EntityUsage="InParts"
    AliasName="PARTCATID"
    LOVName="LovSysPartCatagory">
    <Properties>
      <SchemaBasedProperties>
        <CONTROLTYPE
          Value="input_text_lov"/>
      </SchemaBasedProperties>
    </Properties>
  </ViewAttribute>
  <ViewAttribute
    Name="Uomsid"
    IsNotNull="true"
    PrecisionRule="true"
    EntityAttrName="Uomsid"
    EntityUsage="InParts"
    AliasName="UOMSID"/>
  <ViewAttribute
    Name="Description"
    IsNotNull="true"
    PrecisionRule="true"
    EntityAttrName="Description"
    EntityUsage="InParts"
    AliasName="DESCRIPTION"/>
  <ViewAttribute
    Name="Specification"
    PrecisionRule="true"
    EntityAttrName="Specification"
    EntityUsage="InParts"
    AliasName="SPECIFICATION"/>
  <ViewAttribute
    Name="PartRefId"
    PrecisionRule="true"
    EntityAttrName="PartRefId"
    EntityUsage="InParts"
    AliasName="PART_REF_ID"/>
  <ViewAttribute
    Name="Partno"
    IsUnique="true"
    IsNotNull="true"
    PrecisionRule="true"
    EntityAttrName="Partno"
    EntityUsage="InParts"
    AliasName="PARTNO"/>
  <ViewAttribute
    Name="Childpartno"
    PrecisionRule="true"
    EntityAttrName="Childpartno"
    EntityUsage="InParts"
    AliasName="CHILDPARTNO"/>
  <ViewAttribute
    Name="Partweight"
    PrecisionRule="true"
    EntityAttrName="Partweight"
    EntityUsage="InParts"
    AliasName="PARTWEIGHT"/>
  <ViewAttribute
    Name="Lastpurchrate"
    PrecisionRule="true"
    EntityAttrName="Lastpurchrate"
    EntityUsage="InParts"
    AliasName="LASTPURCHRATE"/>
  <ViewAttribute
    Name="LeadTime"
    PrecisionRule="true"
    EntityAttrName="LeadTime"
    EntityUsage="InParts"
    AliasName="LEAD_TIME"/>
  <ViewAttribute
    Name="DutyPr"
    PrecisionRule="true"
    EntityAttrName="DutyPr"
    EntityUsage="InParts"
    AliasName="DUTY_PR"/>
  <ViewAttribute
    Name="IbPr"
    PrecisionRule="true"
    EntityAttrName="IbPr"
    EntityUsage="InParts"
    AliasName="IB_PR"/>
  <ViewAttribute
    Name="Stax"
    PrecisionRule="true"
    EntityAttrName="Stax"
    EntityUsage="InParts"
    AliasName="STAX"/>
  <ViewAttribute
    Name="Itax"
    PrecisionRule="true"
    EntityAttrName="Itax"
    EntityUsage="InParts"
    AliasName="ITAX"/>
  <ViewAttribute
    Name="Hscode"
    PrecisionRule="true"
    EntityAttrName="Hscode"
    EntityUsage="InParts"
    AliasName="HSCODE"/>
  <ViewAttribute
    Name="HsRate"
    PrecisionRule="true"
    EntityAttrName="HsRate"
    EntityUsage="InParts"
    AliasName="HS_RATE"/>
  <ViewAttribute
    Name="Pglcode"
    PrecisionRule="true"
    EntityAttrName="Pglcode"
    EntityUsage="InParts"
    AliasName="PGLCODE"/>
  <ViewAttribute
    Name="Pccenter"
    PrecisionRule="true"
    EntityAttrName="Pccenter"
    EntityUsage="InParts"
    AliasName="PCCENTER"/>
  <ViewAttribute
    Name="Createdby"
    PrecisionRule="true"
    EntityAttrName="Createdby"
    EntityUsage="InParts"
    AliasName="CREATEDBY"/>
  <ViewAttribute
    Name="CreatedDate"
    PrecisionRule="true"
    EntityAttrName="CreatedDate"
    EntityUsage="InParts"
    AliasName="CREATED_DATE"/>
  <ViewAttribute
    Name="Modifiedby"
    PrecisionRule="true"
    EntityAttrName="Modifiedby"
    EntityUsage="InParts"
    AliasName="MODIFIEDBY"/>
  <ViewAttribute
    Name="ModifiedDate"
    PrecisionRule="true"
    EntityAttrName="ModifiedDate"
    EntityUsage="InParts"
    AliasName="MODIFIED_DATE"/>
  <ViewAttribute
    Name="Needapproval"
    IsNotNull="true"
    PrecisionRule="true"
    EntityAttrName="Needapproval"
    EntityUsage="InParts"
    AliasName="NEEDAPPROVAL"/>
  <ViewAttribute
    Name="Itemid"
    PrecisionRule="true"
    EntityAttrName="Itemid"
    EntityUsage="InParts"
    AliasName="ITEMID">
    <Dependencies>
      <Item
        Value="ProdId"/>
    </Dependencies>
  </ViewAttribute>
  <ViewAttribute
    Name="txtModel"
    PrecisionRule="true"
    EntityAttrName="txtModel"
    EntityUsage="InParts"
    AliasName="TXT_MODEL"
    IsQueriable="false"
    IsPersistent="false"
    LOVName="LovModelInparts">
    <Properties>
      <SchemaBasedProperties>
        <CONTROLTYPE
          Value="input_text_lov"/>
      </SchemaBasedProperties>
    </Properties>
    <Dependencies>
      <Item
        Value="ProdId"/>
    </Dependencies>
  </ViewAttribute>
  <ViewAttribute
    Name="txtPartNameNo"
    IsQueriable="false"
    IsPersistent="false"
    PrecisionRule="true"
    EntityAttrName="txtPartNameNo"
    EntityUsage="InParts"
    AliasName="TXT_PART_NAME_NO"/>
  <ViewCriteria
    Name="InPartsVC"
    ViewObjectName="dgcom.model.vo.srv.InPartsVO"
    Conjunction="AND"
    Mode="3">
    <Properties>
      <CustomProperties>
        <Property
          Name="displayOperators"
          Value="InAdvancedMode"/>
        <Property
          Name="autoExecute"
          Value="false"/>
        <Property
          Name="allowConjunctionOverride"
          Value="false"/>
        <Property
          Name="showInList"
          Value="true"/>
        <Property
          Name="mode"
          Value="Basic"/>
      </CustomProperties>
    </Properties>
    <ViewCriteriaRow
      Name="InPartsVOCriteria_row_0"
      UpperColumns="1">
      <ViewCriteriaItem
        Name="Partid"
        ViewAttribute="Partid"
        Operator="="
        Conjunction="AND"
        GenerateIsNullClauseForBindVars="false"
        Required="Optional">
        <Properties>
          <SchemaBasedProperties>
            <DISPLAYWIDTH
              Value="20"/>
          </SchemaBasedProperties>
        </Properties>
      </ViewCriteriaItem>
      <ViewCriteriaItem
        Name="Description"
        ViewAttribute="Description"
        Operator="CONTAINS"
        Conjunction="AND"
        GenerateIsNullClauseForBindVars="false"
        Required="Optional">
        <Properties>
          <SchemaBasedProperties>
            <DISPLAYWIDTH
              Value="20"/>
          </SchemaBasedProperties>
        </Properties>
      </ViewCriteriaItem>
      <ViewCriteriaItem
        Name="Partno"
        ViewAttribute="Partno"
        Operator="="
        Conjunction="AND"
        GenerateIsNullClauseForBindVars="false"
        Required="Optional">
        <Properties>
          <SchemaBasedProperties>
            <DISPLAYWIDTH
              Value="20"/>
          </SchemaBasedProperties>
        </Properties>
      </ViewCriteriaItem>
    </ViewCriteriaRow>
  </ViewCriteria>
  <ViewCriteria
    Name="InPartsPartExistsInBOMVC"
    ViewObjectName="dgcom.model.vo.srv.InPartsVO"
    Conjunction="AND">
    <Properties>
      <CustomProperties>
        <Property
          Name="displayOperators"
          Value="InAdvancedMode"/>
        <Property
          Name="autoExecute"
          Value="false"/>
        <Property
          Name="allowConjunctionOverride"
          Value="true"/>
        <Property
          Name="showInList"
          Value="true"/>
        <Property
          Name="mode"
          Value="Basic"/>
      </CustomProperties>
    </Properties>
    <ViewCriteriaRow
      Name="InPartsVOCriteria_row_0"
      UpperColumns="1">
      <ViewCriteriaItem
        Name="Partid"
        ViewAttribute="Partid"
        Operator="CONTAINS"
        Conjunction="AND"
        UpperColumns="1"
        GenerateIsNullClauseForBindVars="false"
        Required="Optional">
        <Properties>
          <SchemaBasedProperties>
            <DISPLAYWIDTH
              Value="20"/>
          </SchemaBasedProperties>
        </Properties>
      </ViewCriteriaItem>
      <ViewCriteriaItem
        Name="Description"
        ViewAttribute="Description"
        Operator="CONTAINS"
        Conjunction="AND"
        GenerateIsNullClauseForBindVars="false"
        Required="Optional">
        <Properties>
          <SchemaBasedProperties>
            <DISPLAYWIDTH
              Value="20"/>
          </SchemaBasedProperties>
        </Properties>
      </ViewCriteriaItem>
      <ViewCriteriaItem
        Name="Partno"
        ViewAttribute="Partno"
        Operator="CONTAINS"
        Conjunction="AND"
        GenerateIsNullClauseForBindVars="false"
        Required="Optional">
        <Properties>
          <SchemaBasedProperties>
            <DISPLAYWIDTH
              Value="20"/>
          </SchemaBasedProperties>
        </Properties>
      </ViewCriteriaItem>
    </ViewCriteriaRow>
  </ViewCriteria>
  <ViewCriteria
    Name="InPartsPartExistsInBOMWithItemVC"
    ViewObjectName="dgcom.model.vo.srv.InPartsVO"
    Conjunction="AND">
    <Properties>
      <CustomProperties>
        <Property
          Name="displayOperators"
          Value="InAdvancedMode"/>
        <Property
          Name="autoExecute"
          Value="false"/>
        <Property
          Name="allowConjunctionOverride"
          Value="true"/>
        <Property
          Name="showInList"
          Value="true"/>
        <Property
          Name="mode"
          Value="Basic"/>
      </CustomProperties>
    </Properties>
    <ViewCriteriaRow
      Name="InPartsVOCriteria_row_0"
      UpperColumns="1">
      <ViewCriteriaItem
        Name="Partid"
        ViewAttribute="Partid"
        Operator="CONTAINS"
        Conjunction="AND"
        GenerateIsNullClauseForBindVars="false"
        Required="Optional">
        <Properties>
          <SchemaBasedProperties>
            <DISPLAYWIDTH
              Value="20"/>
          </SchemaBasedProperties>
        </Properties>
      </ViewCriteriaItem>
      <ViewCriteriaItem
        Name="Description"
        ViewAttribute="Description"
        Operator="CONTAINS"
        Conjunction="AND"
        GenerateIsNullClauseForBindVars="false"
        Required="Optional">
        <Properties>
          <SchemaBasedProperties>
            <DISPLAYWIDTH
              Value="20"/>
          </SchemaBasedProperties>
        </Properties>
      </ViewCriteriaItem>
      <ViewCriteriaItem
        Name="Partno"
        ViewAttribute="Partno"
        Operator="CONTAINS"
        Conjunction="AND"
        GenerateIsNullClauseForBindVars="false"
        Required="Optional">
        <Properties>
          <SchemaBasedProperties>
            <DISPLAYWIDTH
              Value="20"/>
          </SchemaBasedProperties>
        </Properties>
      </ViewCriteriaItem>
    </ViewCriteriaRow>
  </ViewCriteria>
  <ViewCriteria
    Name="InPartsPartExistsInBOMBindVariableOrConditionVC"
    ViewObjectName="dgcom.model.vo.srv.InPartsVO"
    Conjunction="AND">
    <Properties>
      <CustomProperties>
        <Property
          Name="displayOperators"
          Value="InAdvancedMode"/>
        <Property
          Name="autoExecute"
          Value="false"/>
        <Property
          Name="allowConjunctionOverride"
          Value="true"/>
        <Property
          Name="showInList"
          Value="true"/>
        <Property
          Name="mode"
          Value="Basic"/>
      </CustomProperties>
    </Properties>
    <ViewCriteriaRow
      Name="InPartsVOCriteria_row_0"
      UpperColumns="1">
      <ViewCriteriaItem
        Name="Partid"
        ViewAttribute="Partid"
        Operator="CONTAINS"
        Conjunction="AND"
        Required="Optional">
        <Properties>
          <SchemaBasedProperties>
            <DISPLAYWIDTH
              Value="20"/>
          </SchemaBasedProperties>
        </Properties>
      </ViewCriteriaItem>
      <ViewCriteriaItem
        Name="Description"
        ViewAttribute="Description"
        Operator="CONTAINS"
        Conjunction="AND"
        Required="Optional">
        <Properties>
          <SchemaBasedProperties>
            <DISPLAYWIDTH
              Value="20"/>
          </SchemaBasedProperties>
        </Properties>
      </ViewCriteriaItem>
      <ViewCriteriaItem
        Name="Partno"
        ViewAttribute="Partno"
        Operator="CONTAINS"
        Conjunction="AND"
        GenerateIsNullClauseForBindVars="false"
        Required="Optional">
        <Properties>
          <SchemaBasedProperties>
            <DISPLAYWIDTH
              Value="20"/>
          </SchemaBasedProperties>
        </Properties>
      </ViewCriteriaItem>
      <ViewCriteriaItem
        Name="Itemid"
        ViewAttribute="Itemid"
        Operator="="
        Conjunction="AND"
        Value=":P_ADF_ITEMID"
        IsBindVarValue="true"
        Required="Optional">
        <Properties>
          <CustomProperties>
            <Property
              Name="renderedMode"
              Value="Never"/>
          </CustomProperties>
        </Properties>
      </ViewCriteriaItem>
      <ViewCriteriaItem
        Name="SrvBompartsVO"
        ViewAttribute="SrvBompartsVO"
        Operator="EXISTS"
        Conjunction="AND"
        IsNestedCriteria="true"
        GenerateIsNullClauseForBindVars="false"
        Required="Optional">
        <ViewCriteria
          Name="SrvBompartsVONestedCriteria"
          ViewObjectName="dgcom.model.vo.srv.SrvBompartsVO"
          Conjunction="AND">
          <ViewCriteriaRow
            Name="SrvBompartsVONestedCriteria_row_0"
            UpperColumns="1">
            <ViewCriteriaItem
              Name="BomId"
              ViewAttribute="BomId"
              Operator="ISNOTBLANK"
              Conjunction="AND"
              GenerateIsNullClauseForBindVars="false"
              Required="Optional">
              <Properties>
                <CustomProperties>
                  <Property
                    Name="renderedMode"
                    Value="Never"/>
                </CustomProperties>
              </Properties>
            </ViewCriteriaItem>
          </ViewCriteriaRow>
        </ViewCriteria>
      </ViewCriteriaItem>
      <ViewCriteriaItem
        Name="SrvPartcategoryVO"
        ViewAttribute="SrvPartcategoryVO"
        Operator="EXISTS"
        Conjunction="AND"
        IsNestedCriteria="true"
        GenerateIsNullClauseForBindVars="false"
        Required="Optional">
        <ViewCriteria
          Name="SrvPartcategoryVONestedCriteria"
          ViewObjectName="dgcom.model.vo.srv.SrvPartcategoryVO"
          Conjunction="AND">
          <ViewCriteriaRow
            Name="SrvPartcategoryVONestedCriteria_row_0"
            UpperColumns="1">
            <ViewCriteriaItem
              Name="SrvPartcategoryVONestedCriteria_SrvPartcategoryVONestedCriteria_row_0_Partcatid"
              ViewAttribute="Partcatid"
              Operator="="
              Conjunction="AND"
              Value=":P_ADF_CATID"
              IsBindVarValue="true"
              Required="Optional">
              <Properties>
                <CustomProperties>
                  <Property
                    Name="renderedMode"
                    Value="Never"/>
                </CustomProperties>
              </Properties>
            </ViewCriteriaItem>
          </ViewCriteriaRow>
        </ViewCriteria>
      </ViewCriteriaItem>
    </ViewCriteriaRow>
  </ViewCriteria>
  <ViewLinkAccessor
    Name="SrvStnpartsVO"
    ViewLink="dgcom.model.vl.srv.InPartsSrvStnPartsPartIdVL"
    Type="oracle.jbo.RowIterator"
    IsUpdateable="false"/>
  <ViewLinkAccessor
    Name="SrvSadjustdetlVO"
    ViewLink="dgcom.model.vl.srv.SysC0015205Link"
    Type="oracle.jbo.RowIterator"
    IsUpdateable="false"/>
  <ViewLinkAccessor
    Name="SrvPsdetlVO"
    ViewLink="dgcom.model.vl.srv.SYS_C0015188Link"
    Type="oracle.jbo.RowIterator"
    IsUpdateable="false"/>
  <ViewLinkAccessor
    Name="SrvStransferdetlVO"
    ViewLink="dgcom.model.vl.srv.SysC0015387Link"
    Type="oracle.jbo.RowIterator"
    IsUpdateable="false"/>
  <ViewLinkAccessor
    Name="SrvStransferdetlVO1"
    ViewLink="dgcom.model.vl.srv.SysC0015385Link"
    Type="oracle.jbo.RowIterator"
    IsUpdateable="false"/>
  <ViewLinkAccessor
    Name="InIpmDetailVO"
    ViewLink="dgcom.model.vl.srv.SysC0091845Link"
    Type="oracle.jbo.RowIterator"
    IsUpdateable="false"/>
  <ViewLinkAccessor
    Name="SrvJobswapVO"
    ViewLink="dgcom.model.vl.srv.SysC0015165Link"
    Type="oracle.jbo.RowIterator"
    IsUpdateable="false"/>
  <ViewLinkAccessor
    Name="ItemPartMappingVO"
    ViewLink="dgcom.model.vl.srv.SysC0091573Link"
    Type="oracle.jbo.RowIterator"
    IsUpdateable="false"/>
  <ViewLinkAccessor
    Name="AllDemandLinesVO"
    ViewLink="dgcom.model.vl.srv.SysC0014611Link"
    Type="oracle.jbo.RowIterator"
    IsUpdateable="false"/>
  <ViewLinkAccessor
    Name="SrvPartcategoryVO"
    ViewLink="dgcom.model.vl.srv.SrvPartCatInPartPartCategoryIdVL"
    Type="oracle.jbo.Row"
    IsUpdateable="false"
    Reversed="true"/>
  <ViewLinkAccessor
    Name="SrvStnrecepartsVO"
    ViewLink="dgcom.model.vl.srv.SysC0015221Link"
    Type="oracle.jbo.RowIterator"
    IsUpdateable="false"/>
  <ViewLinkAccessor
    Name="InItemsVO"
    ViewLink="dgcom.model.vl.srv.SysC0014740Link"
    Type="oracle.jbo.Row"
    Reversed="true"
    IsUpdateable="false"/>
  <ViewLinkAccessor
    Name="SrvBompartsVO"
    ViewLink="dgcom.model.vl.srv.SrvInPartsSrvBomPartsPartIdVL"
    Type="oracle.jbo.RowIterator"
    IsUpdateable="false"/>
  <ClientInterface
    Name="__clientInterface">
    <Method
      Name="executeEmptyRowSet"
      MethodName="executeEmptyRowSet">
      <Return
        Name="_return_type_"
        Type="void"/>
    </Method>
  </ClientInterface>
</ViewObject>
